sc_utils/__init__.py
sc_utils/io.py
sc_utils/markers.py
sc_utils/meta.py
sc_utils/plotting.py
scanpy_utils-0.1.1.dist-info/AUTHORS.rst
scanpy_utils-0.1.1.dist-info/LICENSE
scanpy_utils-0.1.1.dist-info/METADATA
scanpy_utils-0.1.1.dist-info/WHEEL
scanpy_utils-0.1.1.dist-info/top_level.txt
scanpy_utils-0.1.1.dist-info/RECORD
