Metadata-Version: 2.1
Name: scanpy-utils
Version: 0.1.1
Summary: Utility functions for scanpy
Home-page: https://github.com/NUPulmonary/scanpy-utils
Author: Nikolay Markov
Author-email: nikolay.markov@northwestern.edu
License: MIT
Project-URL: Documentation, https://scanpy-utils.readthedocs.io/
Project-URL: Changelog, https://scanpy-utils.readthedocs.io/en/latest/changelog.html
Project-URL: Issue Tracker, https://github.com/NUPulmonary/scanpy-utils/issues
Platform: UNKNOWN
Classifier: Development Status :: 4 - Beta
Classifier: Intended Audience :: Science/Research
Classifier: License :: OSI Approved :: MIT License
Classifier: Operating System :: Unix
Classifier: Operating System :: POSIX
Classifier: Programming Language :: Python
Classifier: Programming Language :: Python :: 3
Classifier: Programming Language :: Python :: 3 :: Only
Classifier: Programming Language :: Python :: 3.7
Classifier: Programming Language :: Python :: 3.8
Classifier: Programming Language :: Python :: 3.9
Classifier: Programming Language :: Python :: Implementation :: CPython
Classifier: Programming Language :: Python :: Implementation :: PyPy
Classifier: Topic :: Scientific/Engineering :: Bio-Informatics
Requires-Python: >=3.7
Requires-Dist: scanpy (>=1.7.0)
